{
  "id": "elec-cable-25",
  "name": "Cable electrique 2.5 mm",
  "brand": "Fodis Cable",
  "category": [
    "Electricite"
  ],
  "description": "Cable pour installation domestique, vendu au rouleau ou au metre.",
  "price": 750,
  "currentPrice": 650,
  "currency": "FCFA",
  "unit": "metre",
  "weight": "Selon longueur",
  "dimensions": "Section 2.5 mm",
  "color": "Rouge / Bleu / Jaune",
  "availability": "Disponible",
  "images": [
    "assets/i3.png"
  ],
  "icon": "data/icons/electricite.svg"
}